{
  "schema": "openclaw.predictive.v1",
  "version": "1.0.0",
  "lastUpdated": "2026-03-24T22:04:58.302Z",
  "config": {
    "window": 3,
    "durationThresholdSeconds": 15,
    "confidenceThreshold": 0.7,
    "cooldownSeconds": 600,
    "maxPredictivePerHour": 2
  },
  "stateHistory": [
    {
      "timestamp": 1773872424,
      "status": "healthy"
    },
    {
      "timestamp": 1774383650,
      "status": "healthy"
    },
    {
      "timestamp": 1774389572,
      "status": "healthy"
    },
    {
      "timestamp": 1774389898,
      "status": "healthy"
    }
  ],
  "predictions": [],
  "statistics": {
    "totalPredictions": 0,
    "truePositives": 0,
    "falsePositives": 0,
    "accuracy": 0,
    "lastPrediction": null
  },
  "hourlyCount": {
    "hour": null,
    "count": 0
  }
}